padder/hdl/padder.v
`timescale 1ns / 10ps
//////////////////////////////////////////////////////////////////////////////////
// Company: University of Oxford
// Engineer: Cristian Bourceanu
//
// Create Date: 17.11.2020 10:54:31
// Design Name: Padder
// Module Name: padder
// Project Name: Hashing Engine
// Target Devices: Alveo U280
// Tool Versions: v1_0
// Description:
//
// Dependencies:
//
// Revision:
// Revision 0.01 - File Created
// Additional Comments:
//
//////////////////////////////////////////////////////////////////////////////////

`define HARD_WIRED
module padder
#(
    // AXI Stream Data Width
    parameter P_M_AXIS_DATA_WIDTH=512,
    parameter P_S_AXIS_DATA_WIDTH=512,
    parameter DATA_BLOCK_REG_WIDTH=512
)
(
// Global Ports
input axi_aclk,
input axi_resetn,

// Control
input [1:0] sha_type,  // msf bit is 0 if SHA224/256 and 1 if SHA384/512
input en,   // 1 if the hashing engine has been enabled by the scheduler

// Master Stream Port
output [(P_M_AXIS_DATA_WIDTH-1):0] m_axis_tdata,
output m_axis_tvalid,
input m_axis_tready,
output reg m_axis_tlast,

// Slave Stream Port
input [(P_S_AXIS_DATA_WIDTH-1):0] s_axis_tdata,
input [((P_M_AXIS_DATA_WIDTH)/8-1):0] s_axis_tkeep,
input s_axis_tvalid,
output wire s_axis_tready,
input s_axis_tlast
);
function integer log2;
    input integer number;
    begin
        log2=0;
         while(2**log2<number) begin
            log2=log2+1;
         end
    end
endfunction // log2

// Function to change endianess of length value
function [63:0] big_endian;
input [63:0] length_value;
`ifdef HARD_WIRED
begin
    big_endian[63:56] = length_value[7:0];
    big_endian[55:48] = length_value[15:8];
    big_endian[47:40] = length_value[23:16];
    big_endian[39:32] = length_value[31:24];
    big_endian[31:24] = length_value[39:32];
    big_endian[23:16] = length_value[47:40];
    big_endian[15: 8] = length_value[55:48];
    big_endian[7 : 0] = length_value[63:56];
end
`else
integer byte;
for(byte=0;byte<8;byte=byte+1)begin
    big_endian[(8-byte)*8-1:(7-byte)*8] = length_value[8*(byte+1)-1:8*byte];
end
`endif
endfunction //big_endian

// ---------- Internal Parameters ------------------
localparam P_S_AXIS_TKEEP_WIDTH=P_M_AXIS_DATA_WIDTH/8;
localparam NUM_BYTES_WIDTH = log2(P_S_AXIS_TKEEP_WIDTH);
localparam LEN_FIELD_BYTES = 8;
localparam LEN_FIELD_WIDTH = 8 * LEN_FIELD_BYTES;

// --------- Registers and wires --------------
// If 32 bytes blocks are needed (SHA256), then use only the R_reg,
// otherwise use both of them
reg [DATA_BLOCK_REG_WIDTH-1:0] R_reg;
reg [DATA_BLOCK_REG_WIDTH-1:0] L_reg;
reg [DATA_BLOCK_REG_WIDTH-1:0] pad;
reg [1:0] reg_status;
reg [NUM_BYTES_WIDTH-1:0] shift_inc;
reg [NUM_BYTES_WIDTH-1:0] shift_measure;
reg [NUM_BYTES_WIDTH-1:0] last_valid_byte;
reg [NUM_BYTES_WIDTH-1:0] next_byte;
reg [31:0] length_low;
reg [31:0] length_high;
reg reg_count;
wire reset;

// Initial values
initial begin
    state = IDLE;
    m_axis_tlast = 0;
    s_axis_tready_fsm = 0;
    s_axis_tready_next = 0;
    reg_status = 2'b00;
    length_low = 0;
    length_high = 0;
    reg_count = 0;
    next_byte = 0;
end


// ----------- Logic -----------
// Transmitting padded message block
assign m_axis_tvalid = sha_type ? reg_status[1] : reg_status[0];
assign m_axis_tdata = sha_type ? L_reg : R_reg;
assign s_axis_tready = (m_axis_tvalid & m_axis_tready | ~reg_status[0] | (sha_type & ~reg_status[1])) & s_axis_tready_fsm;
assign reset = ~axi_resetn;

// FSM dependent wires
// free_reg, empty_reg and complete and indicators for what will be the state at the next clock cycle
assign free_reg = m_axis_tvalid & m_axis_tready | ~reg_status[0] | (sha_type & ~reg_status[1]);
assign empty_reg = m_axis_tvalid & m_axis_tready & (sha_type ? reg_status == 2'b10 : reg_status[0]);
assign last_received = s_axis_tlast & s_axis_tready & s_axis_tvalid;

// Complete when there are available 
// 9 bytes (8bytes len and 1 byte = x80) for SHA256 or 17 bytes for SHA384/512
assign complete = free_reg & (reg_count | ~sha_type[1]) & (next_byte < 56 - 2*sha_type[1]);



// ---------- FSM --------------
//FSM registers
reg [2:0] state, state_next;
reg s_axis_tready_next, s_axis_tready_fsm;
reg m_axis_tlast_next;
localparam IDLE = 0;
localparam FEED = 1;
localparam PAD = 2;
localparam EXTRA_PAD = 3;
localparam WAIT = 4;

/*
******** Feed Data In Logic *******
*/

// Propagate data from R_reg to L_reg if needed
always @(posedge axi_aclk) begin
    if(sha_type[1] & ~reg_status[1]) begin
        L_reg <= R_reg;
        reg_status[1] <= reg_status[0];
    end
end

task count_message;
    input [31:0] length_inc;
    begin
        length_low = length_low + length_inc;
        if(length_low == 0)begin
            length_high = length_high + 1;
        end
    end
endtask : count_message
// Feed R_reg
always @(posedge axi_aclk) begin
    if(reset) begin
        R_reg <= #1 0;
        L_reg <= #1 0;
    end
    else begin
        case(state)
            IDLE: begin
                reg_status <= 2'b00;
                length_low <= 0;
                length_high <= 0;
                reg_count <= 0;
            end

            FEED: begin
                if(free_reg) begin
                    if(s_axis_tvalid) begin

                        if(s_axis_tlast)begin
                            // Find the last valid byte in tdata with binary search
                            last_valid_byte = 0;
                            shift_inc = P_S_AXIS_TKEEP_WIDTH >> 1;
                            shift_measure = P_S_AXIS_TKEEP_WIDTH >> 1;
                            while(shift_inc) begin
                                shift_inc = shift_inc >> 1;
                                if(s_axis_tkeep >> shift_measure)begin
                                    last_valid_byte = shift_measure;
                                    shift_measure = shift_measure + shift_inc;
                                end else begin
                                    shift_measure = shift_measure - shift_inc;
                                end
                            end
                            // Write tdata to R_reg
                            R_reg <= s_axis_tdata;
                            next_byte = last_valid_byte + 1;
                            count_message((last_valid_byte + 1) * 8);
                            if(next_byte == 0) begin    // If there weren't any null bytes in the last frame
                                reg_status[0] <= 1;
                                reg_count <= ~reg_count;
                            end else begin
                                reg_status[0] <= 0;
                            end
                        end
                        else begin  // Write tdata to R_reg and raise the flag for a new register
                            R_reg <= s_axis_tdata;
                            reg_status[0] <= 1;
                            reg_count <= ~reg_count;
                            count_message(DATA_BLOCK_REG_WIDTH);
                        end
                    end
                    else begin  // No message block has been received
                        reg_status[0] <= 0;
                    end
                end
            end

            PAD: begin
                if(free_reg)begin   // If R_reg is not completed or if it will be propagated at the next clock edge, then we can carry on with padding
                    pad = 8'h80 << (8 * next_byte);
                    if(complete) begin // If the length doesn't fit in the padding, just pad with 0s the rest and go to next block
                        // If the length fits, then pad with 0s all but the length bytes and assert tlast
                        // Length is written in big-endian format
                        if(sha_type) begin
                            pad = pad | {big_endian({length_high,length_low}),{16'h00}} << (DATA_BLOCK_REG_WIDTH - LEN_FIELD_WIDTH * 2);
                        end else begin
                            pad = pad | big_endian({length_high,length_low}) << (DATA_BLOCK_REG_WIDTH - LEN_FIELD_WIDTH);
                        end

                    end
                    R_reg <= (R_reg & ((1<<(8 * next_byte)) - 1)) | pad;
                    reg_status[0] <= 1;
                    next_byte = 0;
                    reg_count <= ~reg_count;
                end
            end
            EXTRA_PAD: begin
                if(free_reg) begin
                    if(~reg_count & sha_type) begin // In the case of SHA384/512 verify that an even number of 512b blocks has been created
                        R_reg[DATA_BLOCK_REG_WIDTH-1:0] <= 0;
                        reg_status[0] <= 1;
                    end else begin // Then pad with 0's and append the length value
                        // Length is written in big-endian format
                        // I assumed the length will never surprass 2^64-1, which is a reasonable assumption
                        if(sha_type) begin
                            R_reg <= {big_endian({length_high,length_low}),{16'h00}} << (DATA_BLOCK_REG_WIDTH - LEN_FIELD_WIDTH * 2);
                        end else begin
                            R_reg <= big_endian({length_high,length_low}) << (DATA_BLOCK_REG_WIDTH - LEN_FIELD_WIDTH);
                        end
                        reg_status[0] <= 1;
                        reg_count <= ~reg_count;
                    end
                end
            end
            WAIT: begin
                if(free_reg)begin
                    reg_status[0] <= 0;
                end
            end
        endcase // state
    end
end


// FSM transitions
always @(*) begin
    state_next = state;
    s_axis_tready_next = s_axis_tready;
    m_axis_tlast_next = m_axis_tlast;
    case(state)
        IDLE: begin
            s_axis_tready_next = 0;
            if(free_reg) begin
                state_next = FEED;
                s_axis_tready_next = 1;
            end
        end
        FEED: begin
            s_axis_tready_next = 1;
            if(last_received) begin
                s_axis_tready_next = 0;
                state_next = PAD;
            end
        end
        PAD: begin
            s_axis_tready_next = 0;
            if(free_reg) begin
                if(complete) begin 
                    state_next = WAIT;
                    m_axis_tlast_next = 1;
                end else begin
                    state_next = EXTRA_PAD;
                end
            end
        end
        EXTRA_PAD: begin
            s_axis_tready_next = 0;
            if(complete) begin
                m_axis_tlast_next = 1;
                state_next = WAIT;
            end
        end
        WAIT: begin
            s_axis_tready_next = 0;
            if(empty_reg) begin
                state_next = IDLE;
                m_axis_tlast_next = 0;
            end
        end
    endcase
end

//----------Seq Logic----------------------
always @(posedge axi_aclk)
begin: FSM_SEQ
    if(reset) begin
        state <=IDLE;
        m_axis_tlast <= 0;
        s_axis_tready_fsm <= 0;

    end
    else begin
        state <= state_next;
        s_axis_tready_fsm <= s_axis_tready_next;
        m_axis_tlast <= m_axis_tlast_next;
    end
end

`ifdef COCOTB_SIM
`ifndef VERILATOR // traced differently
initial begin
  $dumpfile ("waveform.vcd");
  $dumpvars (0,padder);
  #1;
end
`endif
`endif

endmodule

padder/test/waveform.vcd
$date
	Wed Dec  2 07:41:42 2020
$end
$version
	Icarus Verilog
$end
$timescale
	1ps
$end
$scope module padder $end
$var wire 1 ! axi_aclk $end
$var wire 1 " axi_resetn $end
$var wire 1 # complete $end
$var wire 1 $ empty_reg $end
$var wire 1 % en $end
$var wire 1 & last_received $end
$var wire 1 ' m_axis_tready $end
$var wire 1 ( reset $end
$var wire 512 ) s_axis_tdata [511:0] $end
$var wire 64 * s_axis_tkeep [63:0] $end
$var wire 1 + s_axis_tlast $end
$var wire 1 , s_axis_tvalid $end
$var wire 2 - sha_type [1:0] $end
$var wire 1 . s_axis_tready $end
$var wire 1 / m_axis_tvalid $end
$var wire 512 0 m_axis_tdata [511:0] $end
$var wire 1 1 free_reg $end
$var reg 512 2 L_reg [511:0] $end
$var reg 512 3 R_reg [511:0] $end
$var reg 6 4 last_valid_byte [5:0] $end
$var reg 32 5 length_high [31:0] $end
$var reg 32 6 length_low [31:0] $end
$var reg 1 7 m_axis_tlast $end
$var reg 1 8 m_axis_tlast_next $end
$var reg 6 9 next_byte [5:0] $end
$var reg 512 : pad [511:0] $end
$var reg 1 ; reg_count $end
$var reg 2 < reg_status [1:0] $end
$var reg 1 = s_axis_tready_fsm $end
$var reg 1 > s_axis_tready_next $end
$var reg 6 ? shift_inc [5:0] $end
$var reg 6 @ shift_measure [5:0] $end
$var reg 3 A state [2:0] $end
$var reg 3 B state_next [2:0] $end
$scope function big_endian $end
$var reg 64 C length_value [63:0] $end
$upscope $end
$scope function log2 $end
$var integer 32 D number [31:0] $end
$upscope $end
$scope begin FSM_SEQ $end
$upscope $end
$scope task count_message $end
$var reg 32 E length_inc [31:0] $end
$upscope $end
$upscope $end
$enddefinitions $end
#0
$dumpvars
bx E
bx D
bx C
b1 B
b0 A
bx @
bx ?
1>
0=
b0 <
0;
bx :
b0 9
08
07
b0 6
b0 5
bx 4
bx 3
bx 2
11
bx 0
0/
0.
b0 -
0,
x+
bx *
bx )
1(
0'
0&
z%
0$
1#
0"
1!
$end
#1000
b0 0
b0 2
b0 3
#5000
0!
#10000
0(
1"
1'
1!
#15000
0!
#20000
1,
0+
b10011010000111111001111100110011111101011001110010100001000110000001011000001001001100110111011101110011101110100100001000100010011100111010010110010110101001110111110011001111110101101101111101101100000001011110000111100010111110011011010011000000101000000111110000011101101100110010000000011111101100000110111100100000101110000010010010010011011010000111100100010111010000110011011111001001101111110010100011101111001010011011000010010100110000000100010111011011100011100111000001000100110111011111110110010110 )
b1111111111111111111111111111111111111111111111111111111111111111 *
1.
1>
1=
b1 A
1!
#25000
0!
#30000
b11011101110100000000011101001110100101001001111100000101110000110001111100001101100111111000011101101110000001101001011111010110001000010100111000010100101001111111111110100010000111000110111001010001110000110101001001001000111100000100011111001100011011101000101010011001011110001001010010001111111010100000001010010110101000000001001010011000111110111010001011001010110110101100111011100010100001010001100010010000011100011110110100101110001000110001100111000111011111100001000010010111010100100010111111100001 )
1>
1#
1.
11
1$
1/
b10011010000111111001111100110011111101011001110010100001000110000001011000001001001100110111011101110011101110100100001000100010011100111010010110010110101001110111110011001111110101101101111101101100000001011110000111100010111110011011010011000000101000000111110000011101101100110010000000011111101100000110111100100000101110000010010010010011011010000111100100010111010000110011011111001001101111110010100011101111001010011011000010010100110000000100010111011011100011100111000001000100110111011111110110010110 0
1;
b1 <
b10011010000111111001111100110011111101011001110010100001000110000001011000001001001100110111011101110011101110100100001000100010011100111010010110010110101001110111110011001111110101101101111101101100000001011110000111100010111110011011010011000000101000000111110000011101101100110010000000011111101100000110111100100000101110000010010010010011011010000111100100010111010000110011011111001001101111110010100011101111001010011011000010010100110000000100010111011011100011100111000001000100110111011111110110010110 3
b1000000000 6
b1000000000 E
1!
#35000
0!
#40000
b11101110101101110000000110001111110110011000110100111001010001001101010000001110001010010101011000001111101101111000110000100111101101100101011001101011010100101000001101101010101110100010110011000011001110010110100111101010011111010000100000110100001110011011001100011101100010000110111011101100111111111101011011110001111110110110011011000001010011001111011110101001110100001111001100110111100000100101001100000100111001010010011111110100100011110010011111000000011001111011010010000011101001000010110110001111 )
b11011101110100000000011101001110100101001001111100000101110000110001111100001101100111111000011101101110000001101001011111010110001000010100111000010100101001111111111110100010000111000110111001010001110000110101001001001000111100000100011111001100011011101000101010011001011110001001010010001111111010100000001010010110101000000001001010011000111110111010001011001010110110101100111011100010100001010001100010010000011100011110110100101110001000110001100111000111011111100001000010010111010100100010111111100001 0
0;
b11011101110100000000011101001110100101001001111100000101110000110001111100001101100111111000011101101110000001101001011111010110001000010100111000010100101001111111111110100010000111000110111001010001110000110101001001001000111100000100011111001100011011101000101010011001011110001001010010001111111010100000001010010110101000000001001010011000111110111010001011001010110110101100111011100010100001010001100010010000011100011110110100101110001000110001100111000111011111100001000010010111010100100010111111100001 3
b10000000000 6
1!
#45000
0!
#50000
b10000011100001001110101110110110111100110111001000100110000101001010000011011100011111001001111101010111000111010011001001000010001001111100011111010011001000010100011010010111100111111110010001101110111001010001111000011000000101110011101011010110111001100000000101111010100111100000100011010111110110010101110001110101011010101111110110111001000010010001110011110111011001001011100100101001110010001100000011011000100000000010010010011000010010110001010100111011110111111000010001000101110110111001110111110100 )
b11101110101101110000000110001111110110011000110100111001010001001101010000001110001010010101011000001111101101111000110000100111101101100101011001101011010100101000001101101010101110100010110011000011001110010110100111101010011111010000100000110100001110011011001100011101100010000110111011101100111111111101011011110001111110110110011011000001010011001111011110101001110100001111001100110111100000100101001100000100111001010010011111110100100011110010011111000000011001111011010010000011101001000010110110001111 0
1;
b11101110101101110000000110001111110110011000110100111001010001001101010000001110001010010101011000001111101101111000110000100111101101100101011001101011010100101000001101101010101110100010110011000011001110010110100111101010011111010000100000110100001110011011001100011101100010000110111011101100111111111101011011110001111110110110011011000001010011001111011110101001110100001111001100110111100000100101001100000100111001010010011111110100100011110010011111000000011001111011010010000011101001000010110110001111 3
b11000000000 6
1!
#55000
0!
#60000
b11011010010010011011111100111010110111100101010011100000100111011111100110101101100000101010010011100100010101001111110100000000010011010001101011101110100000011001011001011010111100101101011100001100101001001101001110000110101110000110011100000001001011011011001001101101000010011101110101111011101100011000011001100001000110010110111111001110110101110001010101100111001001110000011011001011011001110010101000011100111011111111100101001001100101010101001100000001010000011000110001001111000001010100110110001100 )
b10000011100001001110101110110110111100110111001000100110000101001010000011011100011111001001111101010111000111010011001001000010001001111100011111010011001000010100011010010111100111111110010001101110111001010001111000011000000101110011101011010110111001100000000101111010100111100000100011010111110110010101110001110101011010101111110110111001000010010001110011110111011001001011100100101001110010001100000011011000100000000010010010011000010010110001010100111011110111111000010001000101110110111001110111110100 0
0;
b10000011100001001110101110110110111100110111001000100110000101001010000011011100011111001001111101010111000111010011001001000010001001111100011111010011001000010100011010010111100111111110010001101110111001010001111000011000000101110011101011010110111001100000000101111010100111100000100011010111110110010101110001110101011010101111110110111001000010010001110011110111011001001011100100101001110010001100000011011000100000000010010010011000010010110001010100111011110111111000010001000101110110111001110111110100 3
b100000000000 6
1!
#65000
0!
#70000
b10 B
0>
1&
1+
bx011111110111111010111010010110001010001100001110011111011110101111110000111110011111101000011000011011100011000010100000110111011101010010010001101101001000001110111000001011100011111110100101100010100001010000010100111110111110001101111011010111001110101001011000010010110001111000110111111110010101011010011011101001001111001110101000100111101000110101101100 )
b111111111111111111111111111111111111111111111 *
b11011010010010011011111100111010110111100101010011100000100111011111100110101101100000101010010011100100010101001111110100000000010011010001101011101110100000011001011001011010111100101101011100001100101001001101001110000110101110000110011100000001001011011011001001101101000010011101110101111011101100011000011001100001000110010110111111001110110101110001010101100111001001110000011011001011011001110010101000011100111011111111100101001001100101010101001100000001010000011000110001001111000001010100110110001100 0
1;
b11011010010010011011111100111010110111100101010011100000100111011111100110101101100000101010010011100100010101001111110100000000010011010001101011101110100000011001011001011010111100101101011100001100101001001101001110000110101110000110011100000001001011011011001001101101000010011101110101111011101100011000011001100001000110010110111111001110110101110001010101100111001001110000011011001011011001110010101000011100111011111111100101001001100101010101001100000001010000011000110001001111000001010100110110001100 3
b101000000000 6
1!
#75000
0!
#80000
0,
bx )
x+
bx *
0&
0$
0.
0/
18
b100 B
0>
bx011111110111111010111010010110001010001100001110011111011110101111110000111110011111101000011000011011100011000010100000110111011101010010010001101101001000001110111000001011100011111110100101100010100001010000010100111110111110001101111011010111001110101001011000010010110001111000110111111110010101011010011011101001001111001110101000100111101000110101101100 0
0=
b10 A
b0 <
bx011111110111111010111010010110001010001100001110011111011110101111110000111110011111101000011000011011100011000010100000110111011101010010010001101101001000001110111000001011100011111110100101100010100001010000010100111110111110001101111011010111001110101001011000010010110001111000110111111110010101011010011011101001001111001110101000100111101000110101101100 3
b101101101000 6
b101101000 E
b101101 9
b101101 @
b0 ?
b101100 4
1!
#85000
0!
#90000
1,
0+
b111000000101110000010011000001000101101100010011110011011010111011111111000000110101110001000101101001010100111011101101000111110110010000001101000110011100010000110001100011011111010011100101110110111011010010011110010001110101100110101111111100110101101011010011100011001010111011100010110000001010100000010100010011001010000100110000101001011010010101000111101100001011110011011110110101010010000000010011111111101010111001010101101100111000110111010011001001000011000001100000000111001110010111110010100110 )
b1111111111111111111111111111111111111111111111111111111111111111 *
1#
08
b0 B
11
1$
1/
b1101000000010110000000000000000000000000000000000000000000000000000000000000000000000000000000000000000000000000000000000000000000000000000000010000000011111110111111010111010010110001010001100001110011111011110101111110000111110011111101000011000011011100011000010100000110111011101010010010001101101001000001110111000001011100011111110100101100010100001010000010100111110111110001101111011010111001110101001011000010010110001111000110111111110010101011010011011101001001111001110101000100111101000110101101100 0
17
b100 A
0;
b1 <
b1101000000010110000000000000000000000000000000000000000000000000000000000000000000000000000000000000000000000000000000000000000000000000000000010000000011111110111111010111010010110001010001100001110011111011110101111110000111110011111101000011000011011100011000010100000110111011101010010010001101101001000001110111000001011100011111110100101100010100001010000010100111110111110001101111011010111001110101001011000010010110001111000110111111110010101011010011011101001001111001110101000100111101000110101101100 3
b0 9
b101101101000 C
b1101000000010110000000000000000000000000000000000000000000000000000000000000000000000000000000000000000000000000000000000000000000000000000000010000000000000000000000000000000000000000000000000000000000000000000000000000000000000000000000000000000000000000000000000000000000000000000000000000000000000000000000000000000000000000000000000000000000000000000000000000000000000000000000000000000000000000000000000000000000000000000000000000000000000000000000000000000000000000000000000000000000000000000000000000000 :
1!
#95000
0!
#100000
0$
0/
1>
b1 B
07
b0 A
b0 <
1!
#105000
0!
#110000
1.
1>
1=
b1 A
b0 6
1!
#115000
0!
#120000
b1110000000010010100010111111001000111110110111100011100110011111000101011111111111111011000000100010000100101101010111100000111100011100000100010010011011011010101011000010110101110101110001000101110000110101110001101001000110010110111001001110011110001111010111011111111000100000000010011001110110000001100011000001111000011110001101100000010011001001101010010000000110101111000001001101011001011101110111001001101110100000011011010111110100101110011011111110111010001011010110010101111101011100100010110001001 )
1>
1#
1.
11
1$
1/
b111000000101110000010011000001000101101100010011110011011010111011111111000000110101110001000101101001010100111011101101000111110110010000001101000110011100010000110001100011011111010011100101110110111011010010011110010001110101100110101111111100110101101011010011100011001010111011100010110000001010100000010100010011001010000100110000101001011010010101000111101100001011110011011110110101010010000000010011111111101010111001010101101100111000110111010011001001000011000001100000000111001110010111110010100110 0
1;
b1 <
b111000000101110000010011000001000101101100010011110011011010111011111111000000110101110001000101101001010100111011101101000111110110010000001101000110011100010000110001100011011111010011100101110110111011010010011110010001110101100110101111111100110101101011010011100011001010111011100010110000001010100000010100010011001010000100110000101001011010010101000111101100001011110011011110110101010010000000010011111111101010111001010101101100111000110111010011001001000011000001100000000111001110010111110010100110 3
b1000000000 6
b1000000000 E
1!
#125000
0!
#130000
b10000001111000010101111111001101011101010001111000111110010101000011100111010111011111010111100001100010111100100101101100110010000010010100110010111110000001010001110110101001101110010010110011001000111111011010000101101011000000011101111010101100111011110011100001010101101011110100100111111100000110001010110010111010001110001000010101111100110011000101001111010111111010100100100001000100101111100000000011011011001010110110001001100010111011010110000011101110000010010000100100011001001001010010100001000001 )
b1110000000010010100010111111001000111110110111100011100110011111000101011111111111111011000000100010000100101101010111100000111100011100000100010010011011011010101011000010110101110101110001000101110000110101110001101001000110010110111001001110011110001111010111011111111000100000000010011001110110000001100011000001111000011110001101100000010011001001101010010000000110101111000001001101011001011101110111001001101110100000011011010111110100101110011011111110111010001011010110010101111101011100100010110001001 0
0;
b1110000000010010100010111111001000111110110111100011100110011111000101011111111111111011000000100010000100101101010111100000111100011100000100010010011011011010101011000010110101110101110001000101110000110101110001101001000110010110111001001110011110001111010111011111111000100000000010011001110110000001100011000001111000011110001101100000010011001001101010010000000110101111000001001101011001011101110111001001101110100000011011010111110100101110011011111110111010001011010110010101111101011100100010110001001 3
b10000000000 6
1!
#135000
0!
#140000
b10010111001000111100000100010001000100011011101000110010110001010010001010001100010101001101100000101111000000111001000010011010100101101000110101001101100110001100100000010111010001101010101010010000111000111111100101001101001101001001111000101100101011010011100001001111101011010111101000111101100101101010110110010001001101001001010101000011010010111111000101110111001011100101101110111110111110100001011101100111000001101010100110100100111110111100011111001000100010101101101111001110110100111000101110000000 )
b10000001111000010101111111001101011101010001111000111110010101000011100111010111011111010111100001100010111100100101101100110010000010010100110010111110000001010001110110101001101110010010110011001000111111011010000101101011000000011101111010101100111011110011100001010101101011110100100111111100000110001010110010111010001110001000010101111100110011000101001111010111111010100100100001000100101111100000000011011011001010110110001001100010111011010110000011101110000010010000100100011001001001010010100001000001 0
1;
b10000001111000010101111111001101011101010001111000111110010101000011100111010111011111010111100001100010111100100101101100110010000010010100110010111110000001010001110110101001101110010010110011001000111111011010000101101011000000011101111010101100111011110011100001010101101011110100100111111100000110001010110010111010001110001000010101111100110011000101001111010111111010100100100001000100101111100000000011011011001010110110001001100010111011010110000011101110000010010000100100011001001001010010100001000001 3
b11000000000 6
1!
#145000
0!
#150000
b100110100100111110010110101111011100110011111101101000010001111111100100001110001100000011010100000001111111111100110001001010011000011011001000111010011111011111110000100101110110110100110011101010000100000101000111000111011110100000100001010101100110101101011101001001001110100101111110110001110101011010000000110110101100101101111100011110010001001110101101111010101111111011101011111111011100110010010001100111110100111111111011011100001000100101111000011000000111111111000010110010101010110000001001101101 )
b10010111001000111100000100010001000100011011101000110010110001010010001010001100010101001101100000101111000000111001000010011010100101101000110101001101100110001100100000010111010001101010101010010000111000111111100101001101001101001001111000101100101011010011100001001111101011010111101000111101100101101010110110010001001101001001010101000011010010111111000101110111001011100101101110111110111110100001011101100111000001101010100110100100111110111100011111001000100010101101101111001110110100111000101110000000 0
0;
b10010111001000111100000100010001000100011011101000110010110001010010001010001100010101001101100000101111000000111001000010011010100101101000110101001101100110001100100000010111010001101010101010010000111000111111100101001101001101001001111000101100101011010011100001001111101011010111101000111101100101101010110110010001001101001001010101000011010010111111000101110111001011100101101110111110111110100001011101100111000001101010100110100100111110111100011111001000100010101101101111001110110100111000101110000000 3
b100000000000 6
1!
#155000
0!
#160000
b10 B
0>
1&
1+
bx01110111101011011110100110110010100000001000001011111000011010101010111011110110100111001110101111100100100010101111010110010011011110000110110110110111 )
b1111111111111111111 *
b100110100100111110010110101111011100110011111101101000010001111111100100001110001100000011010100000001111111111100110001001010011000011011001000111010011111011111110000100101110110110100110011101010000100000101000111000111011110100000100001010101100110101101011101001001001110100101111110110001110101011010000000110110101100101101111100011110010001001110101101111010101111111011101011111111011100110010010001100111110100111111111011011100001000100101111000011000000111111111000010110010101010110000001001101101 0
1;
b100110100100111110010110101111011100110011111101101000010001111111100100001110001100000011010100000001111111111100110001001010011000011011001000111010011111011111110000100101110110110100110011101010000100000101000111000111011110100000100001010101100110101101011101001001001110100101111110110001110101011010000000110110101100101101111100011110010001001110101101111010101111111011101011111111011100110010010001100111110100111111111011011100001000100101111000011000000111111111000010110010101010110000001001101101 3
b101000000000 6
1!
#165000
0!
#170000
0,
bx )
x+
bx *
0&
0$
0.
0/
18
b100 B
0>
bx01110111101011011110100110110010100000001000001011111000011010101010111011110110100111001110101111100100100010101111010110010011011110000110110110110111 0
0=
b10 A
b0 <
bx01110111101011011110100110110010100000001000001011111000011010101010111011110110100111001110101111100100100010101111010110010011011110000110110110110111 3
b101010011000 6
b10011000 E
b10011 9
b10011 @
b0 ?
b10010 4
1!
#175000
0!
#180000
1,
0+
b100100011111100111111000111101000110001010111110110110100110011100011110010111011110110101110101101011101111011101001001101001100000101100010011011010110001111100111111111101001111000011011001111110101011100011000010000010111100110101101101110111101100001000001111011111101101000001111001001110111001010000000011010110000000001011001001000001011111001000111001111101011110101111000001001001001111100010000010001101000111001001011110100001101111001001001011000110011100111110101111100110101111011110100011100100 )
b1111111111111111111111111111111111111111111111111111111111111111 *
1#
08
b0 B
11
1$
1/
b10011000000010100000000000000000000000000000000000000000000000000000000000000000000000000000000000000000000000000000000000000000000000000000000000000000000000000000000000000000000000000000000000000000000000000000000000000000000000000000000000000000000000000000000000000000000000000000000000000000000000000000000000000000000000000000000000000000000000001000000001110111101011011110100110110010100000001000001011111000011010101010111011110110100111001110101111100100100010101111010110010011011110000110110110110111 0
17
b100 A
0;
b1 <
b10011000000010100000000000000000000000000000000000000000000000000000000000000000000000000000000000000000000000000000000000000000000000000000000000000000000000000000000000000000000000000000000000000000000000000000000000000000000000000000000000000000000000000000000000000000000000000000000000000000000000000000000000000000000000000000000000000000000000001000000001110111101011011110100110110010100000001000001011111000011010101010111011110110100111001110101111100100100010101111010110010011011110000110110110110111 3
b0 9
b101010011000 C
b10011000000010100000000000000000000000000000000000000000000000000000000000000000000000000000000000000000000000000000000000000000000000000000000000000000000000000000000000000000000000000000000000000000000000000000000000000000000000000000000000000000000000000000000000000000000000000000000000000000000000000000000000000000000000000000000000000000000000001000000000000000000000000000000000000000000000000000000000000000000000000000000000000000000000000000000000000000000000000000000000000000000000000000000000000000 :
1!
#185000
0!
#190000
0$
0/
1>
b1 B
07
b0 A
b0 <
1!
#195000
0!
#200000
1.
1>
1=
b1 A
b0 6
1!
#205000
0!
#210000
b10100011101110011010101010110010010111110110111110100001010011010110100100100011110010001000110110011011110111100011010010111011000111110010011001110000000110100010011110101100100011110101011100101111010011000000010010000000001110101100001111000101110111011011000001000000011110011011010010110010101101100110000101101010000011010000111011001111001110010010101000111000011100011101000000110100001001111000101010101000101010000010011100111110010001111101100101001110000011011010101011111001101010001100001001111000 )
1>
1#
1.
11
1$
1/
b100100011111100111111000111101000110001010111110110110100110011100011110010111011110110101110101101011101111011101001001101001100000101100010011011010110001111100111111111101001111000011011001111110101011100011000010000010111100110101101101110111101100001000001111011111101101000001111001001110111001010000000011010110000000001011001001000001011111001000111001111101011110101111000001001001001111100010000010001101000111001001011110100001101111001001001011000110011100111110101111100110101111011110100011100100 0
1;
b1 <
b100100011111100111111000111101000110001010111110110110100110011100011110010111011110110101110101101011101111011101001001101001100000101100010011011010110001111100111111111101001111000011011001111110101011100011000010000010111100110101101101110111101100001000001111011111101101000001111001001110111001010000000011010110000000001011001001000001011111001000111001111101011110101111000001001001001111100010000010001101000111001001011110100001101111001001001011000110011100111110101111100110101111011110100011100100 3
b1000000000 6
b1000000000 E
1!
#215000
0!
#220000
b10010110110100111001001001010000100111000010100110010110010101101000101111010111110001101001110001011000111001111101111010100101111001101011101111111110001100011011101010001010001100000111111000110011000011011010101000101100011010011000100110001010000100011100101110101111110000111000011011001010110000000110001100011111101100101010001011110001000001000110001110110000100111010010101110010100010010110111101010001001010110001001001011011111100010111111011011110010011000110001001101111101000101100101001100111100 )
b10100011101110011010101010110010010111110110111110100001010011010110100100100011110010001000110110011011110111100011010010111011000111110010011001110000000110100010011110101100100011110101011100101111010011000000010010000000001110101100001111000101110111011011000001000000011110011011010010110010101101100110000101101010000011010000111011001111001110010010101000111000011100011101000000110100001001111000101010101000101010000010011100111110010001111101100101001110000011011010101011111001101010001100001001111000 0
0;
b10100011101110011010101010110010010111110110111110100001010011010110100100100011110010001000110110011011110111100011010010111011000111110010011001110000000110100010011110101100100011110101011100101111010011000000010010000000001110101100001111000101110111011011000001000000011110011011010010110010101101100110000101101010000011010000111011001111001110010010101000111000011100011101000000110100001001111000101010101000101010000010011100111110010001111101100101001110000011011010101011111001101010001100001001111000 3
b10000000000 6
1!
#225000
0!
